{
    "aws": {
        "key": "aws",
        "label": "AWS Certification",
        "imageUrl": "/images/aws.svg",
        "url": "https://msggroup.sharepoint.com/sites/msg-ZP/SitePages/en/AWS.aspx"
    },
    "azure": {
        "key": "azure",
        "label": "Azure Certification",
        "imageUrl": "/images/azure.svg",
        "url": "https://msggroup.sharepoint.com/sites/msg-ZP/SitePages/en/Microsoft.aspx"
    },
    "google-cloud": {
        "key": "google-cloud",
        "label": "Google Cloud",
        "imageUrl": "/images/google-cloud.svg",
        "url": "https://msggroup.sharepoint.com/sites/msg-ZP/SitePages/en/Google-Cloud.aspx"
    }
}
